Workbook

Sheet README
A1: TaqatSpace — Milestone Sheet (نسخة المتابعة)
A2: الإصدار 1.0 — 29 أكتوبر 2026. المصدر: TaqatSpace-Milestone-Sheet.md (نفس البيانات).
A4: طريقة الاستخدام:
A5: 1) في ورقة Tasks عدّل فقط الأعمدة المظللة بالأصفر: «الحالة» (قائمة منسدلة) و«الفرع» و«PR» و«ملاحظات».
A6: 2) ورقة Summary تحسب الجهد والمدة ونسبة الإنجاز تلقائيًا بالمعادلات — لا تكتب فيها يدويًا.
A7: 3) الجهد بأيام عمل لمطوّر واحد + Claude؛ المدة = الجهد ÷ 5 أيام.
A8: 4) «قابلة للتأجيل = نعم» تعني أن المهمة خارج المسار الأدنى للانتقال.
A10: مثال لصف مكتمل: الحالة = «✅ مكتمل»، الفرع = feat/m2-mikrotik-sync، PR = #190.
A12: مفتاح الحالة: ⬜ لم يبدأ · 🟨 قيد التنفيذ · ✅ مكتمل · ⛔ متوقف
A13: مفتاح الوضع الحالي: جديد / توسعة (كود قائم يُبنى عليه) / موجود (ربط ومراجعة فقط)
A14: مصدر التقديرات: تقدير أولي ±20% من فريق التطوير (2026-10-29)، يُعاد ضبطه بعد M2.

Sheet Summary
A1: # | B1: Milestone | C1: يعتمد على | D1: الإصدار | E1: الجهد (أيام) | F1: المدة (أسابيع) | G1: نهاية تراكمية (أسبوع) | H1: المنجز (أيام) | I1: نسبة الإنجاز | J1: الجهد بعد التأجيل (أيام)
A2: M0 | B2: التثبيت والجاهزية والاكتشاف | C2: — | D2: R0 | E2: =SUMIFS(Tasks!$G$2:$G$165,Tasks!$B$2:$B$165,A2) | F2: =E2/5 | G2: =SUM($F$2:F2) | H2: =SUMIFS(Tasks!$G$2:$G$165,Tasks!$B$2:$B$165,A2,Tasks!$I$2:$I$165,"✅ مكتمل") | I2: =IFERROR(H2/E2,0) | J2: =SUMIFS(Tasks!$G$2:$G$165,Tasks!$B$2:$B$165,A2,Tasks!$H$2:$H$165,"لا")
A3: M1 | B3: الأساس: المستأجرون والهوية والأدوار والإعدادات | C3: M0 | D3: R1 | E3: =SUMIFS(Tasks!$G$2:$G$165,Tasks!$B$2:$B$165,A3) | F3: =E3/5 | G3: =SUM($F$2:F3) | H3: =SUMIFS(Tasks!$G$2:$G$165,Tasks!$B$2:$B$165,A3,Tasks!$I$2:$I$165,"✅ مكتمل") | I3: =IFERROR(H3/E3,0) | J3: =SUMIFS(Tasks!$G$2:$G$165,Tasks!$B$2:$B$165,A3,Tasks!$H$2:$H$165,"لا")
A4: M2 | B4: تكامل MikroTik (نموذج PUSH) | C4: M1 + VPS | D4: R1 | E4: =SUMIFS(Tasks!$G$2:$G$165,Tasks!$B$2:$B$165,A4) | F4: =E4/5 | G4: =SUM($F$2:F4) | H4: =SUMIFS(Tasks!$G$2:$G$165,Tasks!$B$2:$B$165,A4,Tasks!$I$2:$I$165,"✅ مكتمل") | I4: =IFERROR(H4/E4,0) | J4: =SUMIFS(Tasks!$G$2:$G$165,Tasks!$B$2:$B$165,A4,Tasks!$H$2:$H$165,"لا")
A5: M3 | B5: محرك البيانات: الحضور والإحصاءات والتنبيهات | C5: M2 | D5: R1 | E5: =SUMIFS(Tasks!$G$2:$G$165,Tasks!$B$2:$B$165,A5) | F5: =E5/5 | G5: =SUM($F$2:F5) | H5: =SUMIFS(Tasks!$G$2:$G$165,Tasks!$B$2:$B$165,A5,Tasks!$I$2:$I$165,"✅ مكتمل") | I5: =IFERROR(H5/E5,0) | J5: =SUMIFS(Tasks!$G$2:$G$165,Tasks!$B$2:$B$165,A5,Tasks!$H$2:$H$165,"لا")
A6: M4 | B6: لوحة صاحب المساحة: التشغيل والمشتركون | C6: M3 | D6: R2 | E6: =SUMIFS(Tasks!$G$2:$G$165,Tasks!$B$2:$B$165,A6) | F6: =E6/5 | G6: =SUM($F$2:F6) | H6: =SUMIFS(Tasks!$G$2:$G$165,Tasks!$B$2:$B$165,A6,Tasks!$I$2:$I$165,"✅ مكتمل") | I6: =IFERROR(H6/E6,0) | J6: =SUMIFS(Tasks!$G$2:$G$165,Tasks!$B$2:$B$165,A6,Tasks!$H$2:$H$165,"لا")
A7: M5 | B7: المالية v2: الفوترة والتحصيل ونقطة البيع (بلا بوابة دفع) | C7: M1، M4 | D7: R2 | E7: =SUMIFS(Tasks!$G$2:$G$165,Tasks!$B$2:$B$165,A7) | F7: =E7/5 | G7: =SUM($F$2:F7) | H7: =SUMIFS(Tasks!$G$2:$G$165,Tasks!$B$2:$B$165,A7,Tasks!$I$2:$I$165,"✅ مكتمل") | I7: =IFERROR(H7/E7,0) | J7: =SUMIFS(Tasks!$G$2:$G$165,Tasks!$B$2:$B$165,A7,Tasks!$H$2:$H$165,"لا")
A8: M6 | B8: برنامج GSG وUR وإقفال الشهر | C8: M3، M4 | D8: R3 | E8: =SUMIFS(Tasks!$G$2:$G$165,Tasks!$B$2:$B$165,A8) | F8: =E8/5 | G8: =SUM($F$2:F8) | H8: =SUMIFS(Tasks!$G$2:$G$165,Tasks!$B$2:$B$165,A8,Tasks!$I$2:$I$165,"✅ مكتمل") | I8: =IFERROR(H8/E8,0) | J8: =SUMIFS(Tasks!$G$2:$G$165,Tasks!$B$2:$B$165,A8,Tasks!$H$2:$H$165,"لا")
A9: M7 | B9: التحليلات والتقارير ومنشئ التقارير | C9: M3، M6 | D9: R3 | E9: =SUMIFS(Tasks!$G$2:$G$165,Tasks!$B$2:$B$165,A9) | F9: =E9/5 | G9: =SUM($F$2:F9) | H9: =SUMIFS(Tasks!$G$2:$G$165,Tasks!$B$2:$B$165,A9,Tasks!$I$2:$I$165,"✅ مكتمل") | I9: =IFERROR(H9/E9,0) | J9: =SUMIFS(Tasks!$G$2:$G$165,Tasks!$B$2:$B$165,A9,Tasks!$H$2:$H$165,"لا")
A10: M8 | B10: توسعة لوحة السوبر أدمن | C10: M6 | D10: R3 | E10: =SUMIFS(Tasks!$G$2:$G$165,Tasks!$B$2:$B$165,A10) | F10: =E10/5 | G10: =SUM($F$2:F10) | H10: =SUMIFS(Tasks!$G$2:$G$165,Tasks!$B$2:$B$165,A10,Tasks!$I$2:$I$165,"✅ مكتمل") | I10: =IFERROR(H10/E10,0) | J10: =SUMIFS(Tasks!$G$2:$G$165,Tasks!$B$2:$B$165,A10,Tasks!$H$2:$H$165,"لا")
A11: M9 | B11: توسعة بوابة الفريلانسر | C11: M3، M4، M5 | D11: R4 | E11: =SUMIFS(Tasks!$G$2:$G$165,Tasks!$B$2:$B$165,A11) | F11: =E11/5 | G11: =SUM($F$2:F11) | H11: =SUMIFS(Tasks!$G$2:$G$165,Tasks!$B$2:$B$165,A11,Tasks!$I$2:$I$165,"✅ مكتمل") | I11: =IFERROR(H11/E11,0) | J11: =SUMIFS(Tasks!$G$2:$G$165,Tasks!$B$2:$B$165,A11,Tasks!$H$2:$H$165,"لا")
A12: M10 | B12: الموقع العام ومنشئ الموقع وتسجيل الضيوف | C12: M2، M9 | D12: R4 | E12: =SUMIFS(Tasks!$G$2:$G$165,Tasks!$B$2:$B$165,A12) | F12: =E12/5 | G12: =SUM($F$2:F12) | H12: =SUMIFS(Tasks!$G$2:$G$165,Tasks!$B$2:$B$165,A12,Tasks!$I$2:$I$165,"✅ مكتمل") | I12: =IFERROR(H12/E12,0) | J12: =SUMIFS(Tasks!$G$2:$G$165,Tasks!$B$2:$B$165,A12,Tasks!$H$2:$H$165,"لا")
A13: M11 | B13: التكامل بين اللوحات (End-to-End) | C13: M8، M9، M10 | D13: R5 | E13: =SUMIFS(Tasks!$G$2:$G$165,Tasks!$B$2:$B$165,A13) | F13: =E13/5 | G13: =SUM($F$2:F13) | H13: =SUMIFS(Tasks!$G$2:$G$165,Tasks!$B$2:$B$165,A13,Tasks!$I$2:$I$165,"✅ مكتمل") | I13: =IFERROR(H13/E13,0) | J13: =SUMIFS(Tasks!$G$2:$G$165,Tasks!$B$2:$B$165,A13,Tasks!$H$2:$H$165,"لا")
... A15: M13 | B15: الترحيل وUAT والانتقال الكامل من CoWorkSpaces | C15: M12 | D15: R5 | E15: =SUMIFS(Tasks!$G$2:$G$165,Tasks!$B$2:$B$165,A15) | F15: =E15/5 | G15: =SUM($F$2:F15) | H15: =SUMIFS(Tasks!$G$2:$G$165,Tasks!$B$2:$B$165,A15,Tasks!$I$2:$I$165,"✅ مكتمل") | I15: =IFERROR(H15/E15,0) | J15: =SUMIFS(Tasks!$G$2:$G$165,Tasks!$B$2:$B$165,A15,Tasks!$H$2:$H$165,"لا")
B16: الإجمالي | E16: =SUM(E2:E15) | F16: =SUM(F2:F15) | G16: =G15 | H16: =SUM(H2:H15) | I16: =IFERROR(H16/E16,0) | J16: =SUM(J2:J15)
B18: المدة = الجهد ÷ 5 أيام عمل (مطوّر واحد + Claude، تنفيذ تسلسلي). تقدير أولي ±20% (2026-10-29).
B19: تحقق: مجموع أيام Tasks = SUM(Tasks!G2:G165) | E19: =SUM(Tasks!$G$2:$G$165)

Sheet Tasks
A1: المعرّف | B1: Milestone | C1: المهمة | D1: مرجع SRS | E1: الوضع الحالي في الكود | F1: النوع | G1: الجهد (أيام) | H1: قابلة للتأجيل | I1: الحالة | J1: الفرع | K1: PR | L1: ملاحظات
A2: 0.1 | B2: M0 | C2: إصدار R0: PR من dev إلى main لنشر POS/الكاشير (32 commit) + فحص staging | D2: — | E2: توسعة: 32 commit على dev غير منشورة | F2: Ops | G2: 0.5 | H2: لا | I2: ⬜ لم يبدأ | J2: chore/m0-stabilize
A3: 0.2 | B3: M0 | C3: إزالة مسار ops/clear-cache-9f3a2c غير المحمي | D3: NFR-SEC | E3: توسعة: backend/routes/web.php | F3: BE | G3: 0.25 | H3: لا | I3: ⬜ لم يبدأ | J3: chore/m0-stabilize
A4: 0.3 | B4: M0 | C4: تدوير الأسرار المكشوفة (DB، AWS، Firebase، SSO) ونقلها إلى GitHub Secrets و.env الخادم فقط | D4: NFR-SEC | E4: جديد | F4: Ops | G4: 0.5 | H4: لا | I4: ⬜ لم يبدأ | J4: chore/m0-stabilize
A5: 0.4 | B5: M0 | C5: أمر مجدول subscriptions:expire (لا شيء يحوّل الاشتراك إلى expired حاليًا) بتاريخ الانتهاء فقط — أيام السماح تُضاف في 4.7 + اختبار | D5: FR-MEM-03 | E5: توسعة: backend/routes/console.php | F5: BE | G5: 0.5 | H5: لا | I5: ⬜ لم يبدأ | J5: chore/m0-stabilize
A6: 0.5 | B6: M0 | C6: تجهيز VPS: Nginx، PHP 8.3-FPM، MySQL 8، Redis 7، Supervisor (طوابير ingest/default/heavy)، Certbot، نسخ احتياطي ليلي إلى S3 | D6: NFR-PERF | E6: جديد (الحالي cPanel مشترك بلا worker دائم) | F6: Ops | G6: 1.5 | H6: لا | I6: ⬜ لم يبدأ | J6: chore/m0-stabilize
A7: 0.6 | B7: M0 | C7: النطاق الثابت sync.taqat.space + تحويل GitHub Actions للنشر على الـ VPS (staging ثم production) + systemd لـ Next.js | D7: NFR-PERF | E7: توسعة: .github/workflows/deploy-staging.yml | F7: Ops | G7: 0.75 | H7: لا | I7: ⬜ لم يبدأ | J7: chore/m0-stabilize
A8: 0.7 | B8: M0 | C8: جلب الملحق أ (جرد 80 شاشة) والملحق ب (سكربت MikroTik الحالي من راوتر TAQAT GAZA) وتحديث الشيت إلى v1.1 | D8: — | E8: جديد | F8: PM | G8: 0.5 | H8: لا | I8: ⬜ لم يبدأ | J8: chore/m0-stabilize
A9: 0.8 | B9: M0 | C9: تصدير بيانات CoWorkSpaces (المشتركون، الأجهزة، العقود، Roster، UTR/UR أكتوبر 2026، التقارير) وتوثيق صيغ الملفات | D9: §7.3 | E9: جديد | F9: PM | G9: 0.25 | H9: لا | I9: ⬜ لم يبدأ | J9: chore/m0-stabilize
A10: 0.9 | B10: M0 | C10: تحديث README.md وأرشفة DOCS/taqat_space_dev_plan.xlsx القديم واعتماد هذه الوثائق مرجعًا | D10: — | E10: توسعة: README.md | F10: PM | G10: 0.25 | H10: لا | I10: ⬜ لم يبدأ | J10: chore/m0-stabilize
A11: 0.10 | B11: M0 | C11: جلسة مع مشغّل المنصة (السوبر أدمن) وفريلانسر فعلي لتأكيد نطاق M8/M9 المستنتج في الـ SRS | D11: §5، FR-SA-01..07، FR-FL-01..05 | E11: جديد | F11: PM | G11: 0.5 | H11: لا | I11: ⬜ لم يبدأ | J11: chore/m0-stabilize
A12: 0.11 | B12: M0 | C12: الحصول على مواصفة صيغة UR الكاملة: المعلمات الـ 32، مستويات C، أوزان TypeW، نمط الحضور، الفحوص الـ 22 (شرط لـ 6.4 test-first) | D12: FR-TRK-03، FR-MCL-02 | E12: جديد | F12: PM | G12: 0.5 | H12: لا | I12: ⬜ لم يبدأ | J12: chore/m0-stabilize
A13: 1.1 | B13: M1 | C13: هوية المستأجر: slug ثابت، code فريد (base32)، platform_plan، platform_status + backfill للمساحات الحالية | D13: §1.3، FR-SA-01، ENT-Workspace | E13: توسعة: backend/app/Models/Workspace.php | F13: BE | G13: 0.5 | H13: لا | I13: ⬜ لم يبدأ | J13: feat/m1-foundation
... A165: 13.7 | B165: M13 | C165: Hypercare: مراقبة أسبوع أول + إغلاق أول شهر تشغيل كامل (UR + مطالبة) | D165: — | E165: جديد | F165: الكل | G165: 2.5 | H165: لا | I165: ⬜ لم يبدأ | J165: release/m13-launch

Sheet By Type
A1: النوع | B1: الجهد (أيام) | C1: النسبة
A2: BE | B2: =SUMIFS(Tasks!$G$2:$G$165,Tasks!$F$2:$F$165,A2) | C2: =IFERROR(B2/SUM($B$2:$B$12),0)
A3: BE+FE | B3: =SUMIFS(Tasks!$G$2:$G$165,Tasks!$F$2:$F$165,A3) | C3: =IFERROR(B3/SUM($B$2:$B$12),0)
A4: BE+Ops | B4: =SUMIFS(Tasks!$G$2:$G$165,Tasks!$F$2:$F$165,A4) | C4: =IFERROR(B4/SUM($B$2:$B$12),0)
A5: FE | B5: =SUMIFS(Tasks!$G$2:$G$165,Tasks!$F$2:$F$165,A5) | C5: =IFERROR(B5/SUM($B$2:$B$12),0)
A6: FE+PM | B6: =SUMIFS(Tasks!$G$2:$G$165,Tasks!$F$2:$F$165,A6) | C6: =IFERROR(B6/SUM($B$2:$B$12),0)
A7: Ops | B7: =SUMIFS(Tasks!$G$2:$G$165,Tasks!$F$2:$F$165,A7) | C7: =IFERROR(B7/SUM($B$2:$B$12),0)
A8: PM | B8: =SUMIFS(Tasks!$G$2:$G$165,Tasks!$F$2:$F$165,A8) | C8: =IFERROR(B8/SUM($B$2:$B$12),0)
A9: PM+BE | B9: =SUMIFS(Tasks!$G$2:$G$165,Tasks!$F$2:$F$165,A9) | C9: =IFERROR(B9/SUM($B$2:$B$12),0)
A10: PM+QA | B10: =SUMIFS(Tasks!$G$2:$G$165,Tasks!$F$2:$F$165,A10) | C10: =IFERROR(B10/SUM($B$2:$B$12),0)
A11: QA | B11: =SUMIFS(Tasks!$G$2:$G$165,Tasks!$F$2:$F$165,A11) | C11: =IFERROR(B11/SUM($B$2:$B$12),0)
A12: الكل | B12: =SUMIFS(Tasks!$G$2:$G$165,Tasks!$F$2:$F$165,A12) | C12: =IFERROR(B12/SUM($B$2:$B$12),0)

Sheet Gap Matrix
A1: القسم | B1: المعرّف | C1: المتطلب | D1: الحالة | E1: الموجود حاليًا | F1: الناقص
A2: §2.3 أنواع الاشتراك | B2: SUBTYPE | C2: أنواع الاشتراك: شهري، أسبوعي، يومي، بالساعة، زائر، موظف + طرق تسعير الخطط (ثابت، بالساعات، بالـGB، باقة بحد وصلاحية) | D2: 🟨 | E2: backend/app/Enums/PlanType.php (monthly/daily/custom)، backend/app/Models/Subscription.php، backend/app/Models/InternetPackage.php | F2: إضافة weekly وhourly وvisitor وstaff إلى PlanType؛ نموذج خطة مالية بـ6 طرق تسعير (ساعات/GB/باقة بصلاحية)؛ ربط الاشتراك بالخطة وسعر الزيادة
A3: §2.2 / §6 موظف المساحة | B3: STAFF-01 | C3: دعوة موظف بالبريد + مجموعات جاهزة (صندوق/ضيافة/مشرف مالي) أو صلاحيات فردية | D3: 🟨 | E3: backend/app/Services/Pos/CashierManagementService.php، backend/app/Enums/PosPermission.php (4 صلاحيات POS فقط)، frontend/src/components/features/owner/CashiersManager.tsx | F3: توسيع الدور من "كاشير POS" إلى موظف مساحة عام بصلاحيات مالية (فواتير، مصروفات، أصناف، استيراد، تقارير)؛ مجموعات جاهزة؛ صفحة /settings/staff
A4: §2.2 / §6 موظف المساحة | B4: SEC-2FA | C4: مصادقة ثنائية لإصدار/إلغاء الفواتير (للموظف) | D4: ⬜ | E4: لا يوجد (لا TOTP/OTP في backend/app) | F4: TOTP أو OTP عبر البريد/SMS، تسجيل جهاز، middleware يفرضها على إصدار/إلغاء الفاتورة
A5: §2.2 / §6 موظف المساحة | B5: UX-KBD | C5: اختصارات لوحة المفاتيح (F2 اختيار مشترك، Alt+S/A/R/L) | D5: ⬜ | E5: frontend/src/components/layout/DashShell.tsx (Escape فقط) | F5: hook اختصارات عام، F2 في PosTerminal.tsx، اختصارات اللوحة، مساعدة اختصارات
A6: §3.1 الرئيسية | B6: FR-DSH-01 | C6: درجة صحة المساحة /100 بأربعة مكونات + توصيات | D6: ⬜ | E6: backend/app/Services/OwnerDashboardService.php (إشغال، إيراد فقط) | F6: خوارزمية الدرجة (استخدام/احتفاظ/نشاط/اتصال) وتوصيات نصية؛ تعتمد الاتصال والنشاط على بيانات الحضور غير الموجودة
A7: §3.1 الرئيسية | B7: FR-DSH-02 | C7: بطاقات KPI: نشطون، متصلون الآن، حضور اليوم، UR، تنزيل/رفع، DAU/WAU/MAU، الأجهزة | D7: 🟨 | E7: backend/app/Services/OwnerDashboardService.php، frontend/src/app/[locale]/(dashboard)/owner/page.tsx | F7: الموجود: نشطون، إشغال، مقاعد متاحة، طلبات معلقة، فواتير متأخرة. الناقص: كل بطاقات الشبكة والحضور وUR
A8: §3.1 الرئيسية | B8: FR-DSH-03 | C8: رسوم: نشاط 30 يومًا، توزيع الأنواع، استهلاك الإنترنت، ساعات الذروة، أيام الأسبوع | D8: 🟨 | E8: backend/app/Services/OwnerDashboardService.php (revenue_chart 6 أشهر، members_by_status، members_by_gender)، frontend/src/app/[locale]/(dashboard)/owner/page.tsx | F8: رسوم النشاط والاستهلاك وساعات الذروة وأيام الأسبوع (تتطلب حضور/شبكة)؛ توزيع أنواع الاشتراك بدل الحالة
A9: §3.1 الرئيسية | B9: FR-DSH-04 | C9: النمو والتفاعل: جدد، احتفاظ، معرّضون للتوقف 14+ يومًا، DAU/MAU | D9: ⬜ | E9: لا يوجد (OwnerDashboardService لا يحسبها) | F9: حساب الجدد والاحتفاظ؛ مؤشر التوقف يتطلب بيانات النشاط
A10: §3.1 الرئيسية | B10: FR-DSH-05 | C10: إيراد متوقع، ARPU، نسبة إشغال المقاعد (كتقدير) | D10: 🟨 | E10: backend/app/Services/OwnerDashboardService.php (occupancy_pct، revenue_this_month/last_month) | F10: الإيراد المتوقع وARPU وتوضيح أنه تقدير
A11: §3.1 الرئيسية | B11: FR-DSH-06 | C11: شرائح المشتركين: أبطال، معرّضون، منسحبون، جدد، خاملون، منتظمون | D11: ⬜ | E11: لا يوجد | F11: محرك تقسيم (segmentation) يعتمد سجل الحضور/الاستخدام
A12: §3.1 الرئيسية | B12: FR-DSH-07 | C12: توقع الشهر القادم بانحدار OLS مع R² وموثوقية | D12: ⬜ | E12: لا يوجد | F12: خدمة توقع (OLS) على الإيراد/الحضور وعرض R²
... A137: §7.2 — نموذج البيانات | B137: ENT-ParameterHoliday | C137: معلمات الـ32، تواريخ، حالة طلب | D137: ⬜ | E137: backend/app/Models/SiteSetting.php (مفتاح/قيمة عام) | F137: جديد

Sheet Risks
A1: # | B1: الخطر | C1: الأثر | D1: الاحتمال | E1: التخفيف
A2: R1 | B2: تأخر تجهيز الـ VPS ونقل النشر | C2: تأخير M2 وكل ما بعده | D2: متوسط | E2: يبدأ في M0، والنطاق sync.taqat.space ثابت من اليوم الأول فلا يُعاد تثبيت الراوترات
A3: R2 | B3: اختلاف إصدارات RouterOS وقدرات الراوترات | C3: فشل التثبيت أو الالتقاط | D3: متوسط | E3: CHR + مصفوفة اختبار لإصدارات 7.12+ والموديلات الفعلية
A4: R3 | B4: انقطاع الكهرباء والإنترنت في غزة | C4: فجوات في الحضور تؤثر على UR | D4: عالٍ | E4: seq دائم، مخزن flash، تصحيح انحراف الساعة، وسم أيام الفجوات في UTR
A5: R4 | B5: أسماء مستخدمين مشتركة بين أشخاص | C5: حضور مختلط وتمويل خاطئ | D5: عالٍ | E5: تسجيل الضيوف الذاتي + shared-users=1 + أداة التقسيم حسب MAC
A6: R5 | B6: تنفيذ الراوتر لنص الرد | C6: اختراق الخادم = التحكم بالراوترات | D6: منخفض/حرج | E6: قائمة أوامر مسموحة يفسّرها السكربت منذ M2 (لا تأجيل إلى التقوية)
A7: R6 | B7: دقة صيغة UR مقابل النظام الحالي | C7: رفض الجهة المانحة للتقارير | D7: متوسط | E7: حاسبة نقية test-first + اختبارات ذهبية + مقارنة أشهر التشغيل المتوازي
A8: R7 | B8: تعارض السكربتين أثناء التشغيل المتوازي (خطاف on-login واحد لكل ملف) | C8: تعطيل سكربت CoWorkSpaces | D8: متوسط | E8: وضع «استطلاع فقط» لسكربتنا دون لمس خطافاتهم حتى القطع في M13
A9: R8 | B9: تصدير CoWorkSpaces ناقص (بلا جلسات خام) | C9: صعوبة اختبار المطابقة | D9: متوسط | E9: المطابقة على مستوى UTR والمجاميع + بيانات التشغيل المتوازي
A10: R9 | B10: المالية v2 تكسر الفواتير/POS/الاختبارات القائمة | C10: انحدار في الإنتاج | D10: متوسط | E10: تغييرات إضافية فقط، flag لكل مساحة، مزامنة الحالة القديمة، backfill مختبَر
A11: R10 | B11: مطوّر واحد (سعة واعتمادية) | C11: تأخير وتراكم مراجعات | D11: عالٍ | E11: وكلاء متوازيون في worktrees، المسار الأدنى للانتقال، إعادة تقدير بعد M2
A12: R11 | B12: بيانات شخصية (MAC، الجلسات) | C12: مخاطر خصوصية | D12: متوسط | E12: سياسة احتفاظ (M12.8)، صلاحيات وصول، تدقيق
A13: R12 | B13: الملحق أ (80 شاشة) غير مرئي بعد | C13: نطاق إضافي غير مقدّر | D13: متوسط | E13: مراجعته في M0 وتحديث الشيت إلى v1.1

Sheet Decisions
A1: # | B1: المحور | C1: القرار
A2: D1 | B2: الاتجاه | C2: دمج فوق الموجود: نُبقي الاكتشاف/الحجز/الدردشة/POS/SSO ونضيف طبقة التشغيل
A3: D2 | B3: المالية | C3: مالية كاملة لصاحب المساحة بلا بوابة دفع؛ الخطط تسعير على مستوى المساحة
A4: D3 | B4: الدخول | C4: SSO + ربط اسم مستخدم MikroTik؛ تسجيل ضيف ذاتي من الهوتسبوت؛ لا OTP
A5: D4 | B5: الفريق | C5: مطوّر واحد + Claude؛ مراحل تسلسلية مع وكلاء متوازين داخل كل مرحلة
A6: D5 | B6: الاستضافة | C6: VPS قبل أول راوتر حقيقي (2vCPU/4GB + Redis + Supervisor)؛ sync.taqat.space
A7: D6 | B7: البيانات | C7: تشغيل متوازٍ على راوتر TAQAT GAZA بعد M2؛ ترحيل عبر تصدير CSV/Excel
A8: D7 | B8: تكامل الراوتر | C8: نموذج PUSH (الراوتر يرسل) بدل PULL في DOCS/mikrotik-integration-plan.md
A9: D8 | B9: العقد | C9: توسيع Subscription ليصبح Contract بدل كيان جديد
A10: D9 | B10: المالية v2 | C10: إضافية خلف flag finance_v2 مع مزامنة الحالات القديمة
A11: D10 | B11: UR | C11: حاسبة نقية UrCalculator بإصدارات معلمات غير قابلة للتعديل ونتائج مجمّدة
A12: D11 | B12: المكونات المشتركة | C12: مكونات مشتركة مخصصة: audit_logs، approval_requests، TOTP، phpspreadsheet/phpword
A13: D12 | B13: المخرجات | C13: Markdown + Excel في DOCS/new plan/

Sheet Open Questions
A1: # | B1: السؤال | C1: يؤثر على | D1: الإجابة
A2: 1 | B2: مستويات السوبر أدمن: هل يوجد أكثر من مستوى (مشغّل، مدقق مالي، ممثل مانح)؟ | C2: M8
A3: 2 | B3: هل يرى الفريلانسر ساعاته المرجّحة بعامل C أم الفعلية فقط؟ | C3: M9.3
A4: 3 | B4: الضريبة: هل تُفعَّل لمساحات معينة؟ وبأي معدل؟ | C4: M5.14
A5: 4 | B5: سياسة الاحتفاظ بالبيانات (MAC، الجلسات) وحذفها | C5: M12.8
A6: 5 | B6: هل يحتوي تصدير CoWorkSpaces على UTR لكل مشترك وجلسات خام؟ | C6: M6.1
A7: 6 | B7: هل لدى TAQAT GAZA أكثر من فرع/راوتر حاليًا؟ وما موديل الراوتر وإصدار RouterOS؟ | C7: M1.2، M2.12
A8: 7 | B8: خطط المنصة للمساحات (مجانية/مدفوعة): تتبع يدوي للحالة كما في نموذج العمل الحالي؟ | C8: M8.1
